api_security_tester/__init__.py
api_security_tester-0.2.0.dist-info/METADATA
api_security_tester-0.2.0.dist-info/WHEEL
api_security_tester-0.2.0.dist-info/top_level.txt
api_security_tester-0.2.0.dist-info/RECORD
