Metadata-Version: 2.2
Name: api-security-tester
Version: 0.2.0
Summary: A machine learning based mobile app security testing framework
Home-page: https://github.com/ashinno/APISecurityTester
Author: ASHINNO
Author-email: contact@ashinno.com
Classifier: Development Status :: 3 - Alpha
Classifier: Intended Audience :: Developers
Classifier: Topic :: Security
Classifier: License :: OSI Approved :: MIT License
Classifier: Programming Language :: Python :: 3
Classifier: Programming Language :: Python :: 3.8
Classifier: Programming Language :: Python :: 3.9
Classifier: Programming Language :: Python :: 3.10
Classifier: Programming Language :: Python :: 3.11
Requires-Python: >=3.8
Requires-Dist: numpy>=1.19.0
Requires-Dist: pandas>=1.2.0
Requires-Dist: tensorflow>=2.8.0
Requires-Dist: scikit-learn>=0.24.0
Requires-Dist: pytest>=6.0.0
Requires-Dist: matplotlib>=3.4.0
Dynamic: author
Dynamic: author-email
Dynamic: classifier
Dynamic: description
Dynamic: description-content-type
Dynamic: home-page
Dynamic: requires-dist
Dynamic: requires-python
Dynamic: summary
